{
  "meta": {
    "location": "Schokkerhaven",
    "lat": 52.623,
    "lon": 5.783,
    "models": [
      "icon",
      "ecmwf",
      "jma"
    ],
    "generated_at": "2025-09-22T20:16:45Z",
    "aliases": {
      "icon": "icon_eu",
      "ecmwf": "ecmwf_ifs",
      "jma": "jma_seamless"
    }
  },
  "hours": [
    {
      "time": "2025-09-22T00:00Z",
      "icon": {
        "wind": 4.3,
        "gust": 8.4,
        "dir": 342
      }
    },
    {
      "time": "2025-09-22T01:00Z",
      "icon": {
        "wind": 5.2,
        "gust": 8.6,
        "dir": 347
      }
    },
    {
      "time": "2025-09-22T02:00Z",
      "icon": {
        "wind": 4.7,
        "gust": 8.6,
        "dir": 353
      }
    },
    {
      "time": "2025-09-22T03:00Z",
      "icon": {
        "wind": 4.7,
        "gust": 9.1,
        "dir": 351
      }
    },
    {
      "time": "2025-09-22T04:00Z",
      "icon": {
        "wind": 6.1,
        "gust": 10.1,
        "dir": 353
      }
    },
    {
      "time": "2025-09-22T05:00Z",
      "icon": {
        "wind": 5.1,
        "gust": 10.1,
        "dir": 356
      }
    },
    {
      "time": "2025-09-22T06:00Z",
      "icon": {
        "wind": 5.3,
        "gust": 9.3,
        "dir": 358
      }
    },
    {
      "time": "2025-09-22T07:00Z",
      "icon": {
        "wind": 5.8,
        "gust": 9.9,
        "dir": 2
      }
    },
    {
      "time": "2025-09-22T08:00Z",
      "icon": {
        "wind": 6.4,
        "gust": 11.5,
        "dir": 5
      }
    },
    {
      "time": "2025-09-22T09:00Z",
      "icon": {
        "wind": 9.2,
        "gust": 15.9,
        "dir": 8
      }
    },
    {
      "time": "2025-09-22T10:00Z",
      "icon": {
        "wind": 10.9,
        "gust": 19.0,
        "dir": 12
      }
    },
    {
      "time": "2025-09-22T11:00Z",
      "icon": {
        "wind": 11.1,
        "gust": 19.4,
        "dir": 10
      }
    },
    {
      "time": "2025-09-22T12:00Z",
      "icon": {
        "wind": 10.7,
        "gust": 19.4,
        "dir": 10
      }
    },
    {
      "time": "2025-09-22T13:00Z",
      "icon": {
        "wind": 11.0,
        "gust": 19.4,
        "dir": 9
      }
    },
    {
      "time": "2025-09-22T14:00Z",
      "icon": {
        "wind": 11.0,
        "gust": 19.4,
        "dir": 8
      }
    },
    {
      "time": "2025-09-22T15:00Z",
      "icon": {
        "wind": 11.2,
        "gust": 19.4,
        "dir": 8
      }
    },
    {
      "time": "2025-09-22T16:00Z",
      "icon": {
        "wind": 9.8,
        "gust": 19.2,
        "dir": 7
      }
    },
    {
      "time": "2025-09-22T17:00Z",
      "icon": {
        "wind": 7.2,
        "gust": 16.9,
        "dir": 6
      }
    },
    {
      "time": "2025-09-22T18:00Z",
      "icon": {
        "wind": 5.8,
        "gust": 12.1,
        "dir": 358
      }
    },
    {
      "time": "2025-09-22T19:00Z",
      "icon": {
        "wind": 6.8,
        "gust": 11.9,
        "dir": 357
      }
    },
    {
      "time": "2025-09-22T20:00Z",
      "icon": {
        "wind": 4.1,
        "gust": 11.5,
        "dir": 355
      }
    },
    {
      "time": "2025-09-22T21:00Z",
      "icon": {
        "wind": 2.5,
        "gust": 6.6,
        "dir": 337
      }
    },
    {
      "time": "2025-09-22T22:00Z",
      "icon": {
        "wind": 3.2,
        "gust": 5.1,
        "dir": 322
      }
    },
    {
      "time": "2025-09-22T23:00Z",
      "icon": {
        "wind": 3.5,
        "gust": 5.8,
        "dir": 326
      }
    },
    {
      "time": "2025-09-23T00:00Z",
      "icon": {
        "wind": 3.3,
        "gust": 6.8,
        "dir": 343
      }
    },
    {
      "time": "2025-09-23T01:00Z",
      "icon": {
        "wind": 1.0,
        "gust": 5.2,
        "dir": 349
      }
    },
    {
      "time": "2025-09-23T02:00Z",
      "icon": {
        "wind": 2.2,
        "gust": 3.7,
        "dir": 333
      }
    },
    {
      "time": "2025-09-23T03:00Z",
      "icon": {
        "wind": 4.1,
        "gust": 6.8,
        "dir": 335
      }
    },
    {
      "time": "2025-09-23T04:00Z",
      "icon": {
        "wind": 4.3,
        "gust": 7.2,
        "dir": 336
      }
    },
    {
      "time": "2025-09-23T05:00Z",
      "icon": {
        "wind": 3.5,
        "gust": 7.2,
        "dir": 341
      }
    },
    {
      "time": "2025-09-23T06:00Z",
      "icon": {
        "wind": 3.2,
        "gust": 5.8,
        "dir": 346
      }
    },
    {
      "time": "2025-09-23T07:00Z",
      "icon": {
        "wind": 2.9,
        "gust": 5.2,
        "dir": 4
      }
    },
    {
      "time": "2025-09-23T08:00Z",
      "icon": {
        "wind": 4.2,
        "gust": 7.8,
        "dir": 16
      }
    },
    {
      "time": "2025-09-23T09:00Z",
      "icon": {
        "wind": 6.4,
        "gust": 11.5,
        "dir": 35
      }
    },
    {
      "time": "2025-09-23T10:00Z",
      "icon": {
        "wind": 6.8,
        "gust": 12.2,
        "dir": 39
      }
    },
    {
      "time": "2025-09-23T11:00Z",
      "icon": {
        "wind": 7.3,
        "gust": 13.4,
        "dir": 37
      }
    },
    {
      "time": "2025-09-23T12:00Z",
      "icon": {
        "wind": 9.4,
        "gust": 16.7,
        "dir": 32
      }
    },
    {
      "time": "2025-09-23T13:00Z",
      "icon": {
        "wind": 10.5,
        "gust": 18.3,
        "dir": 35
      }
    },
    {
      "time": "2025-09-23T14:00Z",
      "icon": {
        "wind": 10.7,
        "gust": 19.6,
        "dir": 35
      }
    },
    {
      "time": "2025-09-23T15:00Z",
      "icon": {
        "wind": 11.6,
        "gust": 20.2,
        "dir": 31
      }
    },
    {
      "time": "2025-09-23T16:00Z",
      "icon": {
        "wind": 10.6,
        "gust": 20.2,
        "dir": 31
      }
    },
    {
      "time": "2025-09-23T17:00Z",
      "icon": {
        "wind": 7.8,
        "gust": 18.3,
        "dir": 32
      }
    },
    {
      "time": "2025-09-23T18:00Z",
      "icon": {
        "wind": 7.0,
        "gust": 13.0,
        "dir": 28
      }
    },
    {
      "time": "2025-09-23T19:00Z",
      "icon": {
        "wind": 6.8,
        "gust": 11.7,
        "dir": 37
      }
    },
    {
      "time": "2025-09-23T20:00Z",
      "icon": {
        "wind": 6.1,
        "gust": 11.3,
        "dir": 40
      }
    },
    {
      "time": "2025-09-23T21:00Z",
      "icon": {
        "wind": 6.2,
        "gust": 10.3,
        "dir": 39
      }
    },
    {
      "time": "2025-09-23T22:00Z",
      "icon": {
        "wind": 6.3,
        "gust": 10.9,
        "dir": 43
      }
    },
    {
      "time": "2025-09-23T23:00Z",
      "icon": {
        "wind": 6.0,
        "gust": 10.7,
        "dir": 45
      }
    },
    {
      "time": "2025-09-24T00:00Z",
      "icon": {
        "wind": 6.0,
        "gust": 10.1,
        "dir": 54
      }
    },
    {
      "time": "2025-09-24T01:00Z",
      "icon": {
        "wind": 6.4,
        "gust": 10.7,
        "dir": 55
      }
    },
    {
      "time": "2025-09-24T02:00Z",
      "icon": {
        "wind": 6.5,
        "gust": 11.1,
        "dir": 53
      }
    },
    {
      "time": "2025-09-24T03:00Z",
      "icon": {
        "wind": 7.0,
        "gust": 11.7,
        "dir": 54
      }
    },
    {
      "time": "2025-09-24T04:00Z",
      "icon": {
        "wind": 7.3,
        "gust": 12.4,
        "dir": 53
      }
    },
    {
      "time": "2025-09-24T05:00Z",
      "icon": {
        "wind": 7.5,
        "gust": 12.6,
        "dir": 53
      }
    },
    {
      "time": "2025-09-24T06:00Z",
      "icon": {
        "wind": 7.2,
        "gust": 12.6,
        "dir": 63
      }
    },
    {
      "time": "2025-09-24T07:00Z",
      "icon": {
        "wind": 8.5,
        "gust": 14.8,
        "dir": 66
      }
    },
    {
      "time": "2025-09-24T08:00Z",
      "icon": {
        "wind": 9.8,
        "gust": 17.1,
        "dir": 63
      }
    },
    {
      "time": "2025-09-24T09:00Z",
      "icon": {
        "wind": 10.9,
        "gust": 19.0,
        "dir": 61
      }
    },
    {
      "time": "2025-09-24T10:00Z",
      "icon": {
        "wind": 12.0,
        "gust": 21.2,
        "dir": 76
      }
    },
    {
      "time": "2025-09-24T11:00Z",
      "icon": {
        "wind": 12.8,
        "gust": 22.4,
        "dir": 66
      }
    },
    {
      "time": "2025-09-24T12:00Z",
      "icon": {
        "wind": 13.6,
        "gust": 24.1,
        "dir": 65
      }
    },
    {
      "time": "2025-09-24T13:00Z",
      "icon": {
        "wind": 14.4,
        "gust": 25.5,
        "dir": 62
      }
    },
    {
      "time": "2025-09-24T14:00Z",
      "icon": {
        "wind": 14.6,
        "gust": 25.9,
        "dir": 63
      }
    },
    {
      "time": "2025-09-24T15:00Z",
      "icon": {
        "wind": 14.3,
        "gust": 25.9,
        "dir": 62
      }
    },
    {
      "time": "2025-09-24T16:00Z",
      "icon": {
        "wind": 12.6,
        "gust": 24.9,
        "dir": 59
      }
    },
    {
      "time": "2025-09-24T17:00Z",
      "icon": {
        "wind": 9.6,
        "gust": 21.8,
        "dir": 54
      }
    },
    {
      "time": "2025-09-24T18:00Z",
      "icon": {
        "wind": 8.8,
        "gust": 16.1,
        "dir": 47
      }
    },
    {
      "time": "2025-09-24T19:00Z",
      "icon": {
        "wind": 8.5,
        "gust": 14.6,
        "dir": 47
      }
    },
    {
      "time": "2025-09-24T20:00Z",
      "icon": {
        "wind": 8.7,
        "gust": 14.8,
        "dir": 53
      }
    },
    {
      "time": "2025-09-24T21:00Z",
      "icon": {
        "wind": 9.6,
        "gust": 16.3,
        "dir": 58
      }
    },
    {
      "time": "2025-09-24T22:00Z",
      "icon": {
        "wind": 10.4,
        "gust": 17.5,
        "dir": 60
      }
    },
    {
      "time": "2025-09-24T23:00Z",
      "icon": {
        "wind": 10.4,
        "gust": 17.7,
        "dir": 60
      }
    }
  ]
}