{
  "meta": {
    "location": "Schokkerhaven",
    "lat": 52.623,
    "lon": 5.783,
    "models": [
      "icon",
      "ecmwf",
      "jma"
    ],
    "generated_at": "2025-09-19T15:31:37Z",
    "aliases": {
      "icon": "icon_eu",
      "ecmwf": "ecmwf_ifs",
      "jma": "jma_seamless"
    }
  },
  "hours": [
    {
      "time": "2025-09-19T00:00Z",
      "icon": {
        "wind": 8.7,
        "gust": 14.2,
        "dir": 224
      }
    },
    {
      "time": "2025-09-19T01:00Z",
      "icon": {
        "wind": 8.5,
        "gust": 14.0,
        "dir": 223
      }
    },
    {
      "time": "2025-09-19T02:00Z",
      "icon": {
        "wind": 8.1,
        "gust": 14.0,
        "dir": 222
      }
    },
    {
      "time": "2025-09-19T03:00Z",
      "icon": {
        "wind": 7.9,
        "gust": 13.4,
        "dir": 218
      }
    },
    {
      "time": "2025-09-19T04:00Z",
      "icon": {
        "wind": 7.3,
        "gust": 12.8,
        "dir": 217
      }
    },
    {
      "time": "2025-09-19T05:00Z",
      "icon": {
        "wind": 7.0,
        "gust": 12.2,
        "dir": 210
      }
    },
    {
      "time": "2025-09-19T06:00Z",
      "icon": {
        "wind": 7.0,
        "gust": 11.7,
        "dir": 204
      }
    },
    {
      "time": "2025-09-19T07:00Z",
      "icon": {
        "wind": 7.7,
        "gust": 12.8,
        "dir": 204
      }
    },
    {
      "time": "2025-09-19T08:00Z",
      "icon": {
        "wind": 7.7,
        "gust": 13.4,
        "dir": 204
      }
    },
    {
      "time": "2025-09-19T09:00Z",
      "icon": {
        "wind": 7.4,
        "gust": 13.8,
        "dir": 192
      }
    },
    {
      "time": "2025-09-19T10:00Z",
      "icon": {
        "wind": 7.7,
        "gust": 14.0,
        "dir": 192
      }
    },
    {
      "time": "2025-09-19T11:00Z",
      "icon": {
        "wind": 8.8,
        "gust": 15.4,
        "dir": 188
      }
    },
    {
      "time": "2025-09-19T12:00Z",
      "icon": {
        "wind": 9.4,
        "gust": 16.1,
        "dir": 187
      }
    },
    {
      "time": "2025-09-19T13:00Z",
      "icon": {
        "wind": 9.1,
        "gust": 16.1,
        "dir": 179
      }
    },
    {
      "time": "2025-09-19T14:00Z",
      "icon": {
        "wind": 8.6,
        "gust": 15.6,
        "dir": 181
      }
    },
    {
      "time": "2025-09-19T15:00Z",
      "icon": {
        "wind": 7.6,
        "gust": 14.6,
        "dir": 184
      }
    },
    {
      "time": "2025-09-19T16:00Z",
      "icon": {
        "wind": 5.7,
        "gust": 12.8,
        "dir": 174
      }
    },
    {
      "time": "2025-09-19T17:00Z",
      "icon": {
        "wind": 4.9,
        "gust": 9.5,
        "dir": 162
      }
    },
    {
      "time": "2025-09-19T18:00Z",
      "icon": {
        "wind": 5.6,
        "gust": 9.1,
        "dir": 160
      }
    },
    {
      "time": "2025-09-19T19:00Z",
      "icon": {
        "wind": 5.6,
        "gust": 9.3,
        "dir": 166
      }
    },
    {
      "time": "2025-09-19T20:00Z",
      "icon": {
        "wind": 5.4,
        "gust": 9.1,
        "dir": 167
      }
    },
    {
      "time": "2025-09-19T21:00Z",
      "icon": {
        "wind": 6.1,
        "gust": 10.1,
        "dir": 171
      }
    },
    {
      "time": "2025-09-19T22:00Z",
      "icon": {
        "wind": 6.4,
        "gust": 10.5,
        "dir": 183
      }
    },
    {
      "time": "2025-09-19T23:00Z",
      "icon": {
        "wind": 6.7,
        "gust": 10.9,
        "dir": 187
      }
    },
    {
      "time": "2025-09-20T00:00Z",
      "icon": {
        "wind": 7.1,
        "gust": 11.5,
        "dir": 188
      }
    },
    {
      "time": "2025-09-20T01:00Z",
      "icon": {
        "wind": 7.2,
        "gust": 11.9,
        "dir": 194
      }
    },
    {
      "time": "2025-09-20T02:00Z",
      "icon": {
        "wind": 6.9,
        "gust": 11.9,
        "dir": 196
      }
    },
    {
      "time": "2025-09-20T03:00Z",
      "icon": {
        "wind": 6.9,
        "gust": 17.3,
        "dir": 191
      }
    },
    {
      "time": "2025-09-20T04:00Z",
      "icon": {
        "wind": 7.5,
        "gust": 13.6,
        "dir": 192
      }
    },
    {
      "time": "2025-09-20T05:00Z",
      "icon": {
        "wind": 6.3,
        "gust": 12.2,
        "dir": 202
      }
    },
    {
      "time": "2025-09-20T06:00Z",
      "icon": {
        "wind": 6.2,
        "gust": 10.3,
        "dir": 194
      }
    },
    {
      "time": "2025-09-20T07:00Z",
      "icon": {
        "wind": 6.6,
        "gust": 11.1,
        "dir": 192
      }
    },
    {
      "time": "2025-09-20T08:00Z",
      "icon": {
        "wind": 6.4,
        "gust": 11.1,
        "dir": 182
      }
    },
    {
      "time": "2025-09-20T09:00Z",
      "icon": {
        "wind": 7.2,
        "gust": 12.2,
        "dir": 185
      }
    },
    {
      "time": "2025-09-20T10:00Z",
      "icon": {
        "wind": 9.4,
        "gust": 16.1,
        "dir": 186
      }
    },
    {
      "time": "2025-09-20T11:00Z",
      "icon": {
        "wind": 10.2,
        "gust": 17.3,
        "dir": 198
      }
    },
    {
      "time": "2025-09-20T12:00Z",
      "icon": {
        "wind": 9.0,
        "gust": 17.7,
        "dir": 207
      }
    },
    {
      "time": "2025-09-20T13:00Z",
      "icon": {
        "wind": 9.9,
        "gust": 21.2,
        "dir": 234
      }
    },
    {
      "time": "2025-09-20T14:00Z",
      "icon": {
        "wind": 7.0,
        "gust": 19.4,
        "dir": 214
      }
    },
    {
      "time": "2025-09-20T15:00Z",
      "icon": {
        "wind": 6.4,
        "gust": 16.3,
        "dir": 192
      }
    },
    {
      "time": "2025-09-20T16:00Z",
      "icon": {
        "wind": 9.5,
        "gust": 23.9,
        "dir": 197
      }
    },
    {
      "time": "2025-09-20T17:00Z",
      "icon": {
        "wind": 10.3,
        "gust": 17.5,
        "dir": 192
      }
    },
    {
      "time": "2025-09-20T18:00Z",
      "icon": {
        "wind": 8.9,
        "gust": 17.1,
        "dir": 189
      }
    },
    {
      "time": "2025-09-20T19:00Z",
      "icon": {
        "wind": 9.0,
        "gust": 15.0,
        "dir": 189
      }
    },
    {
      "time": "2025-09-20T20:00Z",
      "icon": {
        "wind": 10.3,
        "gust": 17.3,
        "dir": 191
      }
    },
    {
      "time": "2025-09-20T21:00Z",
      "icon": {
        "wind": 11.9,
        "gust": 19.8,
        "dir": 202
      }
    },
    {
      "time": "2025-09-20T22:00Z",
      "icon": {
        "wind": 11.1,
        "gust": 22.0,
        "dir": 207
      }
    },
    {
      "time": "2025-09-20T23:00Z",
      "icon": {
        "wind": 11.5,
        "gust": 21.8,
        "dir": 206
      }
    },
    {
      "time": "2025-09-21T00:00Z",
      "icon": {
        "wind": 13.1,
        "gust": 22.2,
        "dir": 218
      }
    },
    {
      "time": "2025-09-21T01:00Z",
      "icon": {
        "wind": 15.3,
        "gust": 26.2,
        "dir": 233
      }
    },
    {
      "time": "2025-09-21T02:00Z",
      "icon": {
        "wind": 16.2,
        "gust": 27.8,
        "dir": 227
      }
    },
    {
      "time": "2025-09-21T03:00Z",
      "icon": {
        "wind": 14.3,
        "gust": 27.8,
        "dir": 236
      }
    },
    {
      "time": "2025-09-21T04:00Z",
      "icon": {
        "wind": 15.7,
        "gust": 28.8,
        "dir": 245
      }
    },
    {
      "time": "2025-09-21T05:00Z",
      "icon": {
        "wind": 14.5,
        "gust": 26.6,
        "dir": 245
      }
    },
    {
      "time": "2025-09-21T06:00Z",
      "icon": {
        "wind": 13.0,
        "gust": 24.5,
        "dir": 257
      }
    },
    {
      "time": "2025-09-21T07:00Z",
      "icon": {
        "wind": 11.3,
        "gust": 21.6,
        "dir": 282
      }
    },
    {
      "time": "2025-09-21T08:00Z",
      "icon": {
        "wind": 10.5,
        "gust": 19.0,
        "dir": 281
      }
    },
    {
      "time": "2025-09-21T09:00Z",
      "icon": {
        "wind": 10.3,
        "gust": 17.7,
        "dir": 280
      }
    },
    {
      "time": "2025-09-21T10:00Z",
      "icon": {
        "wind": 9.3,
        "gust": 17.1,
        "dir": 280
      }
    },
    {
      "time": "2025-09-21T11:00Z",
      "icon": {
        "wind": 7.9,
        "gust": 15.9,
        "dir": 279
      }
    },
    {
      "time": "2025-09-21T12:00Z",
      "icon": {
        "wind": 7.8,
        "gust": 14.4,
        "dir": 284
      }
    },
    {
      "time": "2025-09-21T13:00Z",
      "icon": {
        "wind": 7.5,
        "gust": 13.6,
        "dir": 291
      }
    },
    {
      "time": "2025-09-21T14:00Z",
      "icon": {
        "wind": 7.8,
        "gust": 13.8,
        "dir": 297
      }
    },
    {
      "time": "2025-09-21T15:00Z",
      "icon": {
        "wind": 8.4,
        "gust": 14.4,
        "dir": 301
      }
    },
    {
      "time": "2025-09-21T16:00Z",
      "icon": {
        "wind": 7.7,
        "gust": 14.2,
        "dir": 306
      }
    },
    {
      "time": "2025-09-21T17:00Z",
      "icon": {
        "wind": 7.1,
        "gust": 13.2,
        "dir": 307
      }
    },
    {
      "time": "2025-09-21T18:00Z",
      "icon": {
        "wind": 5.3,
        "gust": 11.7,
        "dir": 306
      }
    },
    {
      "time": "2025-09-21T19:00Z",
      "icon": {
        "wind": 5.6,
        "gust": 9.3,
        "dir": 299
      }
    },
    {
      "time": "2025-09-21T20:00Z",
      "icon": {
        "wind": 5.5,
        "gust": 9.1,
        "dir": 293
      }
    },
    {
      "time": "2025-09-21T21:00Z",
      "icon": {
        "wind": 5.2,
        "gust": 9.1,
        "dir": 283
      }
    },
    {
      "time": "2025-09-21T22:00Z",
      "icon": {
        "wind": 4.1,
        "gust": 8.4,
        "dir": 262
      }
    },
    {
      "time": "2025-09-21T23:00Z",
      "icon": {
        "wind": 4.6,
        "gust": 7.4,
        "dir": 250
      }
    }
  ]
}