{
  "meta": {
    "location": "Schokkerhaven",
    "lat": 52.623,
    "lon": 5.783,
    "models": [
      "icon",
      "ecmwf",
      "jma"
    ],
    "generated_at": "2025-08-19T04:53:46Z",
    "aliases": {
      "icon": "icon_eu",
      "ecmwf": "ecmwf_ifs",
      "jma": "jma_seamless"
    }
  },
  "hours": [
    {
      "time": "2025-08-19T00:00Z",
      "icon": {
        "wind": 5.7,
        "gust": 10.3,
        "dir": 52
      }
    },
    {
      "time": "2025-08-19T01:00Z",
      "icon": {
        "wind": 5.4,
        "gust": 9.5,
        "dir": 52
      }
    },
    {
      "time": "2025-08-19T02:00Z",
      "icon": {
        "wind": 5.2,
        "gust": 9.1,
        "dir": 56
      }
    },
    {
      "time": "2025-08-19T03:00Z",
      "icon": {
        "wind": 5.3,
        "gust": 8.9,
        "dir": 51
      }
    },
    {
      "time": "2025-08-19T04:00Z",
      "icon": {
        "wind": 5.1,
        "gust": 8.9,
        "dir": 50
      }
    },
    {
      "time": "2025-08-19T05:00Z",
      "icon": {
        "wind": 5.1,
        "gust": 8.7,
        "dir": 47
      }
    },
    {
      "time": "2025-08-19T06:00Z",
      "icon": {
        "wind": 5.6,
        "gust": 10.1,
        "dir": 44
      }
    },
    {
      "time": "2025-08-19T07:00Z",
      "icon": {
        "wind": 6.3,
        "gust": 11.9,
        "dir": 45
      }
    },
    {
      "time": "2025-08-19T08:00Z",
      "icon": {
        "wind": 6.6,
        "gust": 12.8,
        "dir": 43
      }
    },
    {
      "time": "2025-08-19T09:00Z",
      "icon": {
        "wind": 6.3,
        "gust": 12.6,
        "dir": 43
      }
    },
    {
      "time": "2025-08-19T10:00Z",
      "icon": {
        "wind": 6.5,
        "gust": 12.4,
        "dir": 39
      }
    },
    {
      "time": "2025-08-19T11:00Z",
      "icon": {
        "wind": 6.8,
        "gust": 12.6,
        "dir": 39
      }
    },
    {
      "time": "2025-08-19T12:00Z",
      "icon": {
        "wind": 6.4,
        "gust": 12.4,
        "dir": 35
      }
    },
    {
      "time": "2025-08-19T13:00Z",
      "icon": {
        "wind": 6.5,
        "gust": 12.2,
        "dir": 27
      }
    },
    {
      "time": "2025-08-19T14:00Z",
      "icon": {
        "wind": 7.1,
        "gust": 13.2,
        "dir": 17
      }
    },
    {
      "time": "2025-08-19T15:00Z",
      "icon": {
        "wind": 9.2,
        "gust": 16.9,
        "dir": 7
      }
    },
    {
      "time": "2025-08-19T16:00Z",
      "icon": {
        "wind": 9.8,
        "gust": 17.7,
        "dir": 7
      }
    },
    {
      "time": "2025-08-19T17:00Z",
      "icon": {
        "wind": 10.5,
        "gust": 18.9,
        "dir": 5
      }
    },
    {
      "time": "2025-08-19T18:00Z",
      "icon": {
        "wind": 9.0,
        "gust": 18.7,
        "dir": 9
      }
    },
    {
      "time": "2025-08-19T19:00Z",
      "icon": {
        "wind": 7.7,
        "gust": 15.9,
        "dir": 12
      }
    },
    {
      "time": "2025-08-19T20:00Z",
      "icon": {
        "wind": 5.9,
        "gust": 13.2,
        "dir": 11
      }
    },
    {
      "time": "2025-08-19T21:00Z",
      "icon": {
        "wind": 5.9,
        "gust": 10.1,
        "dir": 9
      }
    },
    {
      "time": "2025-08-19T22:00Z",
      "icon": {
        "wind": 5.3,
        "gust": 10.1,
        "dir": 8
      }
    },
    {
      "time": "2025-08-19T23:00Z",
      "icon": {
        "wind": 4.1,
        "gust": 8.9,
        "dir": 3
      }
    },
    {
      "time": "2025-08-20T00:00Z",
      "icon": {
        "wind": 4.1,
        "gust": 7.2,
        "dir": 355
      }
    },
    {
      "time": "2025-08-20T01:00Z",
      "icon": {
        "wind": 5.1,
        "gust": 8.9,
        "dir": 358
      }
    },
    {
      "time": "2025-08-20T02:00Z",
      "icon": {
        "wind": 4.2,
        "gust": 8.9,
        "dir": 347
      }
    },
    {
      "time": "2025-08-20T03:00Z",
      "icon": {
        "wind": 3.7,
        "gust": 7.2,
        "dir": 342
      }
    },
    {
      "time": "2025-08-20T04:00Z",
      "icon": {
        "wind": 3.7,
        "gust": 7.4,
        "dir": 351
      }
    },
    {
      "time": "2025-08-20T05:00Z",
      "icon": {
        "wind": 4.8,
        "gust": 8.4,
        "dir": 348
      }
    },
    {
      "time": "2025-08-20T06:00Z",
      "icon": {
        "wind": 4.1,
        "gust": 8.2,
        "dir": 343
      }
    },
    {
      "time": "2025-08-20T07:00Z",
      "icon": {
        "wind": 5.8,
        "gust": 11.1,
        "dir": 346
      }
    },
    {
      "time": "2025-08-20T08:00Z",
      "icon": {
        "wind": 5.9,
        "gust": 10.9,
        "dir": 6
      }
    },
    {
      "time": "2025-08-20T09:00Z",
      "icon": {
        "wind": 6.5,
        "gust": 12.2,
        "dir": 46
      }
    },
    {
      "time": "2025-08-20T10:00Z",
      "icon": {
        "wind": 5.8,
        "gust": 11.9,
        "dir": 57
      }
    },
    {
      "time": "2025-08-20T11:00Z",
      "icon": {
        "wind": 7.0,
        "gust": 13.0,
        "dir": 56
      }
    },
    {
      "time": "2025-08-20T12:00Z",
      "icon": {
        "wind": 7.7,
        "gust": 14.0,
        "dir": 63
      }
    },
    {
      "time": "2025-08-20T13:00Z",
      "icon": {
        "wind": 7.3,
        "gust": 14.4,
        "dir": 61
      }
    },
    {
      "time": "2025-08-20T14:00Z",
      "icon": {
        "wind": 8.7,
        "gust": 16.1,
        "dir": 51
      }
    },
    {
      "time": "2025-08-20T15:00Z",
      "icon": {
        "wind": 9.5,
        "gust": 17.5,
        "dir": 51
      }
    },
    {
      "time": "2025-08-20T16:00Z",
      "icon": {
        "wind": 10.0,
        "gust": 17.9,
        "dir": 47
      }
    },
    {
      "time": "2025-08-20T17:00Z",
      "icon": {
        "wind": 10.8,
        "gust": 18.9,
        "dir": 38
      }
    },
    {
      "time": "2025-08-20T18:00Z",
      "icon": {
        "wind": 10.2,
        "gust": 19.2,
        "dir": 33
      }
    },
    {
      "time": "2025-08-20T19:00Z",
      "icon": {
        "wind": 8.2,
        "gust": 17.9,
        "dir": 25
      }
    },
    {
      "time": "2025-08-20T20:00Z",
      "icon": {
        "wind": 7.6,
        "gust": 14.0,
        "dir": 26
      }
    },
    {
      "time": "2025-08-20T21:00Z",
      "icon": {
        "wind": 7.2,
        "gust": 13.0,
        "dir": 27
      }
    },
    {
      "time": "2025-08-20T22:00Z",
      "icon": {
        "wind": 7.2,
        "gust": 12.4,
        "dir": 24
      }
    },
    {
      "time": "2025-08-20T23:00Z",
      "icon": {
        "wind": 7.2,
        "gust": 12.6,
        "dir": 24
      }
    },
    {
      "time": "2025-08-21T00:00Z",
      "icon": {
        "wind": 6.6,
        "gust": 12.4,
        "dir": 28
      }
    },
    {
      "time": "2025-08-21T01:00Z",
      "icon": {
        "wind": 6.3,
        "gust": 11.3,
        "dir": 26
      }
    },
    {
      "time": "2025-08-21T02:00Z",
      "icon": {
        "wind": 5.8,
        "gust": 10.7,
        "dir": 21
      }
    },
    {
      "time": "2025-08-21T03:00Z",
      "icon": {
        "wind": 5.2,
        "gust": 9.7,
        "dir": 15
      }
    },
    {
      "time": "2025-08-21T04:00Z",
      "icon": {
        "wind": 5.3,
        "gust": 8.9,
        "dir": 8
      }
    },
    {
      "time": "2025-08-21T05:00Z",
      "icon": {
        "wind": 5.5,
        "gust": 9.3,
        "dir": 6
      }
    },
    {
      "time": "2025-08-21T06:00Z",
      "icon": {
        "wind": 6.5,
        "gust": 11.1,
        "dir": 7
      }
    },
    {
      "time": "2025-08-21T07:00Z",
      "icon": {
        "wind": 8.4,
        "gust": 15.0,
        "dir": 3
      }
    },
    {
      "time": "2025-08-21T08:00Z",
      "icon": {
        "wind": 11.1,
        "gust": 20.2,
        "dir": 11
      }
    },
    {
      "time": "2025-08-21T09:00Z",
      "icon": {
        "wind": 10.8,
        "gust": 20.0,
        "dir": 6
      }
    },
    {
      "time": "2025-08-21T10:00Z",
      "icon": {
        "wind": 10.7,
        "gust": 19.6,
        "dir": 4
      }
    },
    {
      "time": "2025-08-21T11:00Z",
      "icon": {
        "wind": 10.5,
        "gust": 19.6,
        "dir": 4
      }
    },
    {
      "time": "2025-08-21T12:00Z",
      "icon": {
        "wind": 11.3,
        "gust": 20.8,
        "dir": 360
      }
    },
    {
      "time": "2025-08-21T13:00Z",
      "icon": {
        "wind": 10.7,
        "gust": 20.6,
        "dir": 358
      }
    },
    {
      "time": "2025-08-21T14:00Z",
      "icon": {
        "wind": 10.9,
        "gust": 21.2,
        "dir": 1
      }
    },
    {
      "time": "2025-08-21T15:00Z",
      "icon": {
        "wind": 12.7,
        "gust": 22.9,
        "dir": 355
      }
    },
    {
      "time": "2025-08-21T16:00Z",
      "icon": {
        "wind": 12.1,
        "gust": 23.1,
        "dir": 358
      }
    },
    {
      "time": "2025-08-21T17:00Z",
      "icon": {
        "wind": 11.9,
        "gust": 22.4,
        "dir": 359
      }
    },
    {
      "time": "2025-08-21T18:00Z",
      "icon": {
        "wind": 9.7,
        "gust": 21.0,
        "dir": 359
      }
    },
    {
      "time": "2025-08-21T19:00Z",
      "icon": {
        "wind": 6.6,
        "gust": 17.1,
        "dir": 355
      }
    },
    {
      "time": "2025-08-21T20:00Z",
      "icon": {
        "wind": 5.3,
        "gust": 11.3,
        "dir": 350
      }
    },
    {
      "time": "2025-08-21T21:00Z",
      "icon": {
        "wind": 5.0,
        "gust": 9.1,
        "dir": 334
      }
    },
    {
      "time": "2025-08-21T22:00Z",
      "icon": {
        "wind": 4.7,
        "gust": 8.4,
        "dir": 330
      }
    },
    {
      "time": "2025-08-21T23:00Z",
      "icon": {
        "wind": 4.7,
        "gust": 8.2,
        "dir": 336
      }
    }
  ]
}